CMakeLists.txt
LICENSE
MANIFEST.in
README.md
VERSION
pyproject.toml
pytest.ini
requirements.txt
setup.cfg
setup.py
cmake/Modules/KokkosPythonBuildOptions.cmake
cmake/Modules/KokkosPythonCompilers.cmake
cmake/Modules/KokkosPythonFormat.cmake
cmake/Modules/KokkosPythonKokkos.cmake
cmake/Modules/KokkosPythonOptions.cmake
cmake/Modules/KokkosPythonPackages.cmake
cmake/Modules/KokkosPythonSetup.cmake
cmake/Modules/KokkosPythonUtilities.cmake
cmake/Templates/KokkosExp_InterOp.hpp
cmake/Templates/demangle.cpp
examples/CMakeLists.txt
examples/ex-generate.cpp
examples/ex-numpy.py
examples/user.cpp
examples/user.hpp
external/CMakeLists.txt
external/kokkos/.clang-format
external/kokkos/.clang-format-ignore
external/kokkos/.clang-tidy
external/kokkos/.codecov.yml
external/kokkos/.jenkins
external/kokkos/.travis.yml
external/kokkos/BUILD.md
external/kokkos/CHANGELOG.md
external/kokkos/CMakeLists.txt
external/kokkos/CONTRIBUTING.md
external/kokkos/Copyright.txt
external/kokkos/HOW_TO_SNAPSHOT
external/kokkos/LICENSE
external/kokkos/Makefile.kokkos
external/kokkos/Makefile.targets
external/kokkos/README.md
external/kokkos/Spack.md
external/kokkos/appveyor.yml
external/kokkos/generate_makefile.bash
external/kokkos/gnu_generate_makefile.bash
external/kokkos/master_history.txt
external/kokkos/.github/workflows/cancelling.yml
external/kokkos/.github/workflows/continuous-integration-workflow.yml
external/kokkos/.github/workflows/osx.yml
external/kokkos/algorithms/CMakeLists.txt
external/kokkos/algorithms/cmake/Dependencies.cmake
external/kokkos/algorithms/cmake/KokkosAlgorithms_config.h.in
external/kokkos/algorithms/src/CMakeLists.txt
external/kokkos/algorithms/src/KokkosAlgorithms_dummy.cpp
external/kokkos/algorithms/src/Kokkos_Random.hpp
external/kokkos/algorithms/src/Kokkos_Sort.hpp
external/kokkos/algorithms/unit_tests/CMakeLists.txt
external/kokkos/algorithms/unit_tests/Makefile
external/kokkos/algorithms/unit_tests/TestOpenMP_Sort1D.cpp
pykokkos_base.egg-info/PKG-INFO
pykokkos_base.egg-info/SOURCES.txt
pykokkos_base.egg-info/dependency_links.txt
pykokkos_base.egg-info/not-zip-safe
pykokkos_base.egg-info/requires.txt
pykokkos_base.egg-info/top_level.txt
