Metadata-Version: 2.1
Name: pykokkos-base
Version: 0.0.7
Summary: Python bindings to Kokkos Views for data interop
Home-page: http://github.com/kokkos/kokkos-python
Author: Jonathan R. Madsen
Author-email: jrmadsen@lbl.gov
Maintainer: Jonathan R. Madsen
Maintainer-email: jrmadsen@lbl.gov
License: BSD 3-Clause License
Download-URL: http://github.com/kokkos/kokkos-python.git
Project-URL: kokkos, https://github.com/kokkos/kokkos
Keywords: kokkos,parallelism,performance,performance portability,gpu,cuda,hip,rocm,hpx,openmp,openmptarget,sycl,serial
Platform: UNKNOWN
Classifier: Development Status :: 4 - Beta
Classifier: Environment :: GPU
Classifier: Environment :: GPU :: NVIDIA CUDA
Classifier: Intended Audience :: Developers
Classifier: Intended Audience :: Science/Research
Classifier: Natural Language :: English
Classifier: License :: OSI Approved :: BSD License
Classifier: Operating System :: MacOS
Classifier: Operating System :: Microsoft :: Windows
Classifier: Operating System :: POSIX :: Linux
Classifier: Operating System :: POSIX :: BSD
Classifier: Operating System :: Unix
Classifier: Programming Language :: C++
Classifier: Programming Language :: Python :: 3
Classifier: Programming Language :: Python :: 3.6
Classifier: Programming Language :: Python :: 3.7
Classifier: Programming Language :: Python :: 3.8
Classifier: Programming Language :: Python :: 3.9
Classifier: Programming Language :: Python :: 3.10
Classifier: Topic :: Scientific/Engineering
